[{
  "_id": {
    "$oid": "5f3a3f9d16fea61128c02732"
  },
  "picking_id": {
    "$oid": "5f3a3f9b16fea61128c02730"
  },
  "move_id": {
    "$oid": "5f3a3f9c16fea61128c02731"
  },
  "location_source_id": {
    "$oid": "5f27aa6f456dd126b089a1e3"
  },
  "location_dest_id": {
    "$oid": "5f27aedb251bce1b05bb4101"
  },
  "product_uom_id": {
    "$oid": "5f1e71113236dd208c4464e8"
  },
  "product_id": {
    "$oid": "5f1e7245c0ff3a1bec9cff07"
  },
  "picking_type": "IN",
  "status": "done",
  "create_date": 1597652893000,
  "create_uid": {
    "$oid": "5f1e604447ba1b17e8a518e6"
  },
  "write_date": 1597653396000,
  "write_uid": {
    "$oid": "5f1e604447ba1b17e8a518e6"
  },
  "line_in_id": "",
  "product_qty": 0,
  "reserved_qty": 0,
  "qty_done": 200,
  "date_done": 1597653396000,
  "company_id": {
    "$oid": "5f1e5dc247ba1b17e8a518dd"
  },
  "line_out_ids": [
    {
      "_id": {
        "$oid": "5f3aada8fead3e198cc0b524"
      },
      "qty": 200
    }
  ]
},{
  "_id": {
    "$oid": "5f3a45c04669580bb8967225"
  },
  "picking_id": {
    "$oid": "5f3a45be4669580bb8967223"
  },
  "move_id": {
    "$oid": "5f3a45bf4669580bb8967224"
  },
  "location_source_id": {
    "$oid": "5f27aa6f456dd126b089a1e3"
  },
  "location_dest_id": {
    "$oid": "5f27aedb251bce1b05bb4101"
  },
  "product_uom_id": {
    "$oid": "5f1e71113236dd208c4464e8"
  },
  "product_id": {
    "$oid": "5f1e7245c0ff3a1bec9cff07"
  },
  "picking_type": "IN",
  "status": "done",
  "create_date": 1597654464000,
  "create_uid": {
    "$oid": "5f1e604447ba1b17e8a518e6"
  },
  "write_date": 1597654474000,
  "write_uid": {
    "$oid": "5f1e604447ba1b17e8a518e6"
  },
  "line_in_id": "",
  "product_qty": 0,
  "reserved_qty": 0,
  "qty_done": 300,
  "date_done": 1597654473000,
  "company_id": {
    "$oid": "5f1e5dc247ba1b17e8a518dd"
  },
  "line_out_ids": [
    {
      "_id": {
        "$oid": "5f3aada8fead3e198cc0b525"
      },
      "qty": 300
    }
  ]
},{
  "_id": {
    "$oid": "5f3aada8fead3e198cc0b524"
  },
  "move_id": {
    "$oid": "5f3aa353fead3e198cc0b520"
  },
  "product_id": {
    "$oid": "5f1e7245c0ff3a1bec9cff07"
  },
  "location_dest_id": {
    "$oid": "5f27afe519967f1de42d2829"
  },
  "location_source_id": {
    "$oid": "5f27aedb251bce1b05bb4101"
  },
  "picking_type": "OUT",
  "picking_id": {
    "$oid": "5f3aa353fead3e198cc0b51f"
  },
  "status": "assigned",
  "product_uom_id": {
    "$oid": "5f1e71113236dd208c4464ec"
  },
  "reserved_qty": 200,
  "line_in_id": {
    "$oid": "5f3a3f9d16fea61128c02732"
  },
  "create_date": 1597681064000,
  "create_uid": {
    "$oid": "5f1e5fe647ba1b17e8a518e3"
  },
  "write_date": 1597681064000,
  "write_uid": {
    "$oid": "5f1e5fe647ba1b17e8a518e3"
  },
  "product_qty": 0,
  "qty_done": 0,
  "date_done": 0,
  "company_id": {
    "$oid": "5f1e5dc247ba1b17e8a518dd"
  }
},{
  "_id": {
    "$oid": "5f3aada8fead3e198cc0b525"
  },
  "move_id": {
    "$oid": "5f3aa353fead3e198cc0b520"
  },
  "product_id": {
    "$oid": "5f1e7245c0ff3a1bec9cff07"
  },
  "location_dest_id": {
    "$oid": "5f27afe519967f1de42d2829"
  },
  "location_source_id": {
    "$oid": "5f27aedb251bce1b05bb4101"
  },
  "picking_type": "OUT",
  "picking_id": {
    "$oid": "5f3aa353fead3e198cc0b51f"
  },
  "status": "assigned",
  "product_uom_id": {
    "$oid": "5f1e71113236dd208c4464ec"
  },
  "reserved_qty": 300,
  "line_in_id": {
    "$oid": "5f3a45c04669580bb8967225"
  },
  "create_date": 1597681064000,
  "create_uid": {
    "$oid": "5f1e5fe647ba1b17e8a518e3"
  },
  "write_date": 1597681064000,
  "write_uid": {
    "$oid": "5f1e5fe647ba1b17e8a518e3"
  },
  "product_qty": 0,
  "qty_done": 0,
  "date_done": 0,
  "company_id": {
    "$oid": "5f1e5dc247ba1b17e8a518dd"
  }
}]